FooFinder/__init__.py
FooFinder-3.0.60.dist-info/LICENSE
FooFinder-3.0.60.dist-info/METADATA
FooFinder-3.0.60.dist-info/WHEEL
FooFinder-3.0.60.dist-info/top_level.txt
FooFinder-3.0.60.dist-info/RECORD
