Metadata-Version: 2.1
Name: FooFinder
Version: 3.0.60
Summary: A package designed to help you find foo.
Home-page: https://github.com/MadisonAster/FooFinder
Author: Madison Aster
Author-email: info@MadisonAster.com
License: LGPL
Keywords: relative imports importing recursive
Platform: UNKNOWN
Classifier: Development Status :: 5 - Production/Stable
Classifier: Intended Audience :: Developers
Classifier: Topic :: Software Development
Classifier: License :: OSI Approved :: GNU General Public License v3 or later (GPLv3+)
Classifier: Programming Language :: Python :: 3.5
Classifier: Programming Language :: Python :: 3.6
Classifier: Programming Language :: Python :: 3.7
Classifier: Programming Language :: Python :: 3.8
Classifier: Programming Language :: Python :: 3.9
Classifier: Programming Language :: Python :: 3.10
Requires-Python: >3.5.0
